cli/__init__.py
cli/commands.py
cli/main.py
compliant_llm-0.1.9.dist-info/licenses/LICENSE
core/__init__.py
core/reporter.py
core/runner.py
core/analytics/__init__.py
core/analytics/client.py
core/analytics/settings.py
core/analytics/tracker.py
core/compliance_mappings/__init__.py
core/compliance_mappings/base.py
core/compliance_mappings/genai_redteam_compliance_mapping.yaml
core/compliance_mappings/orchestrator.py
core/compliance_mappings/gdpr/__init__.py
core/compliance_mappings/gdpr/adapter.py
core/compliance_mappings/gdpr/controls_reference.yaml
core/compliance_mappings/gdpr/documentation_requirements.yaml
core/compliance_mappings/gdpr/gdpr_data_protection_principles.yaml
core/compliance_mappings/gdpr/gdpr_user_rights.yaml
core/compliance_mappings/gdpr/risk_scoring.yaml
core/compliance_mappings/gdpr/strategy_mapping.yaml
core/compliance_mappings/nist/__init__.py
core/compliance_mappings/nist/adapter.py
core/compliance_mappings/nist/const.py
core/compliance_mappings/nist/loaders.py
core/compliance_mappings/nist/mapper.py
core/compliance_mappings/nist/reporter.py
core/compliance_mappings/nist/mappings/controls_reference.yaml
core/compliance_mappings/nist/mappings/documentation_requirements.yaml
core/compliance_mappings/nist/mappings/risk_scoring.yaml
core/compliance_mappings/nist/mappings/strategy_mapping.yaml
core/config_manager/__init__.py
core/config_manager/cli_adapter.py
core/config_manager/config.py
core/config_manager/ui_adapter.py
core/data_models/__init__.py
core/data_store/__init__.py
core/data_store/model_config_store.py
core/evaluators/__init__.py
core/evaluators/base.py
core/evaluators/evals/__init__.py
core/evaluators/evals/advanced_evaluators.py
core/evaluators/evals/attack_evaluator.py
core/evaluators/evals/compliance.py
core/providers/__init__.py
core/providers/base.py
core/providers/litellm_provider.py
core/strategies/__init__.py
core/strategies/base.py
core/strategies/const.py
core/strategies/attack_strategies/__init__.py
core/strategies/attack_strategies/owasp_strategy.py
compliant_llm-0.1.9.dist-info/METADATA
compliant_llm-0.1.9.dist-info/WHEEL
compliant_llm-0.1.9.dist-info/entry_points.txt
compliant_llm-0.1.9.dist-info/top_level.txt
compliant_llm-0.1.9.dist-info/RECORD
