Metadata-Version: 2.4
Name: compliant-llm
Version: 0.1.9
Summary: Tool for testing AI system prompts against various attack vectors
Home-page: https://github.com/fiddlecube/compliant-llm
Author: Compliant LLM Contributors
Author-email: Compliant LLM Contributors <example@example.com>
License: MIT
Requires-Python: >=3.9
License-File: LICENSE
Requires-Dist: pyyaml
Requires-Dist: streamlit
Requires-Dist: click
Requires-Dist: rich
Requires-Dist: litellm
Requires-Dist: python-dotenv
Requires-Dist: pytest
Requires-Dist: pytest-asyncio
Requires-Dist: aiofiles
Requires-Dist: plotly
Requires-Dist: psutil
Requires-Dist: tinydb
Requires-Dist: markdown
Requires-Dist: opentelemetry-api
Requires-Dist: opentelemetry-sdk
Requires-Dist: opentelemetry-exporter-otlp
Requires-Dist: opentelemetry-instrumentation
Requires-Dist: azure-monitor-opentelemetry-exporter
Requires-Dist: azure-core
Requires-Dist: azure-identity
Requires-Dist: azure-monitor-opentelemetry
Dynamic: author
Dynamic: home-page
Dynamic: license-file
Dynamic: requires-python
